sumologiccse/__init__.py
sumologiccse/sumologiccse.py
sumologiccse-0.2.1.dist-info/METADATA
sumologiccse-0.2.1.dist-info/WHEEL
sumologiccse-0.2.1.dist-info/licenses/LICENSE
sumologiccse-0.2.1.dist-info/RECORD
