Metadata-Version: 2.4
Name: sumologiccse
Version: 0.2.1
Summary: Python SDK for Sumo Logic Cloud SIEM API
Project-URL: Homepage, https://github.com/rjury-sumo/sumologic-cse-python-sdk
Project-URL: Repository, https://github.com/rjury-sumo/sumologic-cse-python-sdk
Project-URL: Bug Tracker, https://github.com/rjury-sumo/sumologic-cse-python-sdk/issues
Project-URL: Documentation, https://github.com/rjury-sumo/sumologic-cse-python-sdk#readme
Author-email: Rick Jury <rjury@sumologic.com>
License-Expression: MIT
License-File: LICENSE
Keywords: api,cloud-siem,cse,python,sdk,security,sumo,sumologic
Classifier: Development Status :: 4 - Beta
Classifier: Intended Audience :: Developers
Classifier: Intended Audience :: System Administrators
Classifier: License :: OSI Approved :: MIT License
Classifier: Operating System :: OS Independent
Classifier: Programming Language :: Python :: 3
Classifier: Programming Language :: Python :: 3.9
Classifier: Programming Language :: Python :: 3.10
Classifier: Programming Language :: Python :: 3.11
Classifier: Programming Language :: Python :: 3.12
Classifier: Programming Language :: Python :: 3.13
Classifier: Topic :: Internet :: WWW/HTTP
Classifier: Topic :: Security
Classifier: Topic :: Software Development :: Libraries :: Python Modules
Requires-Python: >=3.9
Requires-Dist: requests>=2.32.0
Provides-Extra: dev
Requires-Dist: black>=25.1.0; extra == 'dev'
Requires-Dist: build>=1.0.0; extra == 'dev'
Requires-Dist: mypy>=1.17.0; extra == 'dev'
Requires-Dist: pytest-cov>=6.0.0; extra == 'dev'
Requires-Dist: pytest>=8.4.0; extra == 'dev'
Requires-Dist: ruff>=0.8.0; extra == 'dev'
Requires-Dist: twine>=6.0.0; extra == 'dev'
